s4/__init__.py
s4/cli.py
s4/diff.py
s4/inotify_recursive.py
s4/progressbar.py
s4/resolution.py
s4/sync.py
s4/utils.py
s4/clients/__init__.py
s4/clients/local.py
s4/clients/s3.py
s4/commands/__init__.py
s4/commands/add_command.py
s4/commands/daemon_command.py
s4/commands/edit_command.py
s4/commands/ls_command.py
s4/commands/rm_command.py
s4/commands/sync_command.py
s4/commands/targets_command.py
S4-0.4.4.dist-info/LICENSE
S4-0.4.4.dist-info/METADATA
S4-0.4.4.dist-info/WHEEL
S4-0.4.4.dist-info/entry_points.txt
S4-0.4.4.dist-info/top_level.txt
S4-0.4.4.dist-info/RECORD
