Metadata-Version: 2.1
Name: S4
Version: 0.4.4
Summary: Fast and cheap synchronisation of files using Amazon S3
Home-page: https://github.com/MichaelAquilina/S4
Author: Michael Aquilina
Author-email: michaelaquilina@gmail.com
License: GPLv3
Keywords: aws s3 backup sync
Platform: UNKNOWN
Classifier: Environment :: Console
Classifier: Intended Audience :: Developers
Classifier: Natural Language :: English
Classifier: License :: OSI Approved :: GNU General Public License v3 (GPLv3)
Classifier: Programming Language :: Python
Classifier: Programming Language :: Python :: 3
Classifier: Programming Language :: Python :: 3.5
Classifier: Programming Language :: Python :: 3.6
Classifier: Programming Language :: Python :: Implementation :: CPython
Requires-Python: >=3.5
Requires-Dist: boto3 (>=1.9)
Requires-Dist: clint (>=0.5.1)
Requires-Dist: filelock (>=2.0.12)
Requires-Dist: python-magic (>=0.4.12)
Requires-Dist: tabulate (>=0.7.7)
Requires-Dist: tqdm (>=4.8.4)
Requires-Dist: inotify-simple (>=1.1.7)
Requires-Dist: pathspec (>=0.5.6)
